odoo/addons/web_widget_prefixed_url/README.rst
odoo/addons/web_widget_prefixed_url/__init__.py
odoo/addons/web_widget_prefixed_url/__manifest__.py
odoo/addons/web_widget_prefixed_url/i18n/web_widget_prefixed_url.pot
odoo/addons/web_widget_prefixed_url/static/description/icon.png
odoo/addons/web_widget_prefixed_url/static/src/js/widget_prefixed_url.js
odoo/addons/web_widget_prefixed_url/views/template.xml
odoo11_addon_web_widget_prefixed_url-11.0.1.0.0.99.dev1.dist-info/METADATA
odoo11_addon_web_widget_prefixed_url-11.0.1.0.0.99.dev1.dist-info/WHEEL
odoo11_addon_web_widget_prefixed_url-11.0.1.0.0.99.dev1.dist-info/top_level.txt
odoo11_addon_web_widget_prefixed_url-11.0.1.0.0.99.dev1.dist-info/RECORD
